Color_Match/__init__.py
Color_Match/color_match.py
Color_Match/color_match_tmp.py
Color_Match/lin2012xyz10e_fine_7sf.csv
Color_Match-0.0.1.dist-info/LICENSE
Color_Match-0.0.1.dist-info/METADATA
Color_Match-0.0.1.dist-info/WHEEL
Color_Match-0.0.1.dist-info/top_level.txt
Color_Match-0.0.1.dist-info/RECORD
