Metadata-Version: 2.1
Name: Color-Match
Version: 0.0.1
Summary: Utility functions for generating perceptually equivalent colors to a known spectrum using specific, available, wavelength sources.
Home-page: https://github.com/carpdiem/Color-Match
Author: Michael Woods
Author-email: mail@michaelwoods.us
License: MIT
Platform: UNKNOWN
Classifier: Programming Language :: Python :: 3
Classifier: License :: OSI Approved :: MIT License
Classifier: Operating System :: OS Independent
Requires-Python: >=3.6
Requires-Dist: numpy
Requires-Dist: wheel
